Metadata-Version: 1.0
Name: simpledistributions
Version: 0.1
Summary: Gaussian, Poisson and Binomial distributions
Home-page: UNKNOWN
Author: UNKNOWN
Author-email: UNKNOWN
License: UNKNOWN
Platform: UNKNOWN
